CHANGES.txt
DEPENDENCIES.txt
README.txt
bootstrap.py
buildout.cfg
setup.py
src/ks/__init__.py
src/ks.schema.egg-info/PKG-INFO
src/ks.schema.egg-info/SOURCES.txt
src/ks.schema.egg-info/dependency_links.txt
src/ks.schema.egg-info/namespace_packages.txt
src/ks.schema.egg-info/not-zip-safe
src/ks.schema.egg-info/requires.txt
src/ks.schema.egg-info/top_level.txt
src/ks/schema/__init__.py
src/ks/schema/configure.zcml
src/ks/schema/browser/__init__.py
src/ks/schema/browser/simplewidgetfactory.py
src/ks/schema/bytes/__init__.py
src/ks/schema/bytes/configure.zcml
src/ks/schema/bytes/browser/__init__.py
src/ks/schema/bytes/browser/configure.zcml
src/ks/schema/bytes/browser/directfileuploadwidget.py
src/ks/schema/bytes/locales/en/LC_MESSAGES/ks.schema.bytes.po
src/ks/schema/bytes/locales/ru/LC_MESSAGES/ks.schema.bytes.mo
src/ks/schema/bytes/locales/ru/LC_MESSAGES/ks.schema.bytes.po
src/ks/schema/captcha/__init__.py
src/ks/schema/captcha/captcha.py
src/ks/schema/captcha/captcha.txt
src/ks/schema/captcha/configure.zcml
src/ks/schema/captcha/interfaces.py
src/ks/schema/captcha/browser/__init__.py
src/ks/schema/captcha/browser/captchawidget.py
src/ks/schema/captcha/browser/captchawidget.txt
src/ks/schema/captcha/browser/configure.zcml
src/ks/schema/captcha/demo/__init__.py
src/ks/schema/captcha/demo/captchademo.py
src/ks/schema/captcha/demo/configure.zcml
src/ks/schema/captcha/demo/interfaces.py
src/ks/schema/captcha/demo/browser/__init__.py
src/ks/schema/captcha/demo/browser/configure.zcml
src/ks/schema/captcha/demo/etc/ks.field.captcha.demo-configure.zcml
src/ks/schema/captcha/locales/en/LC_MESSAGES/ks.schema.captcha.po
src/ks/schema/captcha/locales/ru/LC_MESSAGES/ks.schema.captcha.mo
src/ks/schema/captcha/locales/ru/LC_MESSAGES/ks.schema.captcha.po
src/ks/schema/date/__init__.py
src/ks/schema/date/configure.zcml
src/ks/schema/date/browser/__init__.py
src/ks/schema/date/browser/calendarwidget.py
src/ks/schema/date/browser/configure.zcml
src/ks/schema/date/browser/interfaces.py
src/ks/schema/date/browser/selectdatewidget.py
src/ks/schema/date/browser/selectdatewidget.txt
src/ks/schema/date/browser/resources/calendar-helper.js
src/ks/schema/date/browser/resources/jscalendar/ChangeLog
src/ks/schema/date/browser/resources/jscalendar/README
